calculadora_basica/__init__.py
calculadora_basica/__main__.py
calculadora_basica/calculadora_basica.py
calculadora_basica-0.0.2.dist-info/METADATA
calculadora_basica-0.0.2.dist-info/WHEEL
calculadora_basica-0.0.2.dist-info/top_level.txt
calculadora_basica-0.0.2.dist-info/RECORD
