Metadata-Version: 2.1
Name: calculadora_basica
Version: 0.0.2
Summary: Uma simples calculadora GUI
Home-page: https://github.com/FawkesC05/DIO-repo/tree/main/Geracao-Tech_Unimed-BH_DS/calculadora_basica
Author: FawkesC05
Author-email: fawkesc05@gmail.com
License: UNKNOWN
Platform: UNKNOWN
Requires-Python: >=3.8
